{
    "bftpd": {
        "pattern": "bftpd(?:\\s+([\\d.]+))?",
        "version": 1
    },
    "Microsoft FTP": {
        "pattern": "Microsoft FTP"
    },
    "WFTPD": {
        "pattern": "WFTPD(?:\\s+([\\d.]+))?",
        "version": 1
    },
    "FileZilla": {
        "pattern": "FileZilla Server(?:\\s+(?:v|(?:\\S+\\s+))?([\\d.]+))?",
        "version": 1
    },
    "DiskStation": {
        "pattern": "DiskStation"
    },
    "ProFTPD": {
        "pattern": "(?:([\\d.a-z]+) Server.*\\()?ProFTPD",
        "version": 1
    },
    "vsftpd": {
        "pattern": "vsFTPd(?:\\s+(?:v|(?:version\\s+))?([\\d.]+))?",
        "version": 1
    },
    "Pure-FTPd": {
        "pattern": "Pure-FTPd"
    },
    "Serv-U": {
        "pattern": "Serv-U FTP Server(?:\\s+(?:v|(?:version\\s+))?([\\d.]+))?",
        "version": 1
    },
    "Windows FTP": {
        "pattern": "Windows ftp server"
    },
    "MikroTik": {
        "pattern": "MikroTik(?:\\s+(?:v|(?:version\\s+))?([\\d.]+))?",
        "version": 1
    },
    "SmbFTPD": {
        "pattern": "SmbFTPD(?:\\s+(?:v|(?:\\S+\\s+))?([\\d.]+))?",
        "version": 1
    },
    "ucftpd": {
        "pattern": "ucftpd"
    },
    "TYPSoft": {
        "pattern": "TYPSoft FTP Server(?:\\s+(?:v|(?:version\\s+))?([\\d.]+))?",
        "version": 1
    },
    "Wing FTP": {
        "pattern": "Wing FTP"
    },
    "Gene6 FTP": {
        "pattern": "Gene6 FTP Server(?:\\s+(?:v|(?:version\\s+))?([\\d.]+))?",
        "version": 1
    },
    "Xlight FTP": {
        "pattern": "Xlight FTP Server(?:\\s+(?:v|(?:version\\s+))?([\\d.]+))?",
        "version": 1
    },
    "EasyFZS": {
        "pattern": "EasyFZS Server(?:\\s+(?:v|(?:version\\s+))?([\\d.]+))?",
        "version": 1
    },
    "freeFTPd": {
        "pattern": "freeFTPd(?:\\s+(?:v|(?:version\\s+))?([\\d.]+))?",
        "version": 1
    },
    "ASUS": {
        "pattern": "Welcome to ASUS (\\S+) FTP service",
        "version": 1
    }
}